fisher/__init__.py
fisher/_version.py
fisher/cfisher.cp37-win_amd64.pyd
fisher/tableprinter.py
fisher-0.1.14.dist-info/LICENSE
fisher-0.1.14.dist-info/METADATA
fisher-0.1.14.dist-info/WHEEL
fisher-0.1.14.dist-info/top_level.txt
fisher-0.1.14.dist-info/zip-safe
fisher-0.1.14.dist-info/RECORD
