Metadata-Version: 2.1
Name: fisher
Version: 0.1.14
Summary: Fast Fisher's Exact Test
Home-page: http://github.com/brentp/fishers_exact_test
Author: Haibao Tang, Brent Pedersen
Author-email: bpederse@gmail.com
License: BSD
Keywords: statistics cython
Classifier: Development Status :: 3 - Alpha
Classifier: Intended Audience :: Developers
Classifier: Intended Audience :: Science/Research
Classifier: License :: OSI Approved :: BSD License
Classifier: Operating System :: OS Independent
Classifier: Programming Language :: Python
Classifier: Topic :: Scientific/Engineering
Classifier: Programming Language :: Python :: 2
Classifier: Programming Language :: Python :: 3
License-File: LICENSE
Requires-Dist: numpy
